{
    "Notif":[
        {
            "head1" :"changelog" ,
            "date1" : "Dec 14,2020",
            "text1" : "A feature has been added that allows the user to call a person who is saved as a pre-configured SOS message contact.",
            "head2" :"Announcement" ,
            "date2" : "Dec 13,2020",
            "text2" : "Lorem Ipsum is simply dummy text of the printing and typesetting."
        },
        {
            "head1" :"changelog" ,
            "date1" : "Dec 14,2020",
            "text1" : "A feature has been added that allows the user to call a person who is saved as a pre-configured SOS message contact.",
            "head2" :"Announcement" ,
            "date2" : "Dec 13,2020",
            "text2" : "Lorem Ipsum is simply dummy text of the printing and typesetting."
        },
        {
            "head1" :"changelog" ,
            "date1" : "Dec 14,2020",
            "text1" : "A feature has been added that allows the user to call a person who is saved as a pre-configured SOS message contact.",
            "head2" :"Announcement" ,
            "date2" : "Dec 13,2020",
            "text2" : "Lorem Ipsum is simply dummy text of the printing and typesetting."
        },
        {
            "head1" :"changelog" ,
            "date1" : "Dec 14,2020",
            "text1" : "A feature has been added that allows the user to call a person who is saved as a pre-configured SOS message contact.",
            "head2" :"Announcement" ,
            "date2" : "Dec 13,2020",
            "text2" : "Lorem Ipsum is simply dummy text of the printing and typesetting."
        },
        {
            "head1" :"changelog" ,
            "date1" : "Dec 14,2020",
            "text1" : "A feature has been added that allows the user to call a person who is saved as a pre-configured SOS message contact.",
            "head2" :"Announcement" ,
            "date2" : "Dec 13,2020",
            "text2" : "Lorem Ipsum is simply dummy text of the printing and typesetting."
        },
        {
            "head1" :"changelog" ,
            "date1" : "Dec 14,2020",
            "text1" : "A feature has been added that allows the user to call a person who is saved as a pre-configured SOS message contact.",
            "head2" :"Announcement" ,
            "date2" : "Dec 13,2020",
            "text2" : "Lorem Ipsum is simply dummy text of the printing and typesetting."
        }
    ]
}